{"client_full_id":"client-job-go-4s-60c-1m-4-zzz8t-15","server_ip":"server-service","server_port":8080,"messages_sent":1,"messages_received":1,"connection_success":true,"total_latency_ms":0.442995,"errors":[],"average_latency_ms":0.442995}
{"client_full_id":"client-job-go-4s-60c-1m-4-zzz8t-13","server_ip":"server-service","server_port":8080,"messages_sent":1,"messages_received":1,"connection_success":true,"total_latency_ms":0.976706,"errors":[],"average_latency_ms":0.976706}
{"client_full_id":"client-job-go-4s-60c-1m-4-zzz8t-39","server_ip":"server-service","server_port":8080,"messages_sent":1,"messages_received":1,"connection_success":true,"total_latency_ms":0.259203,"errors":[],"average_latency_ms":0.259203}
{"client_full_id":"client-job-go-4s-60c-1m-4-zzz8t-10","server_ip":"server-service","server_port":8080,"messages_sent":1,"messages_received":1,"connection_success":true,"total_latency_ms":0.842289,"errors":[],"average_latency_ms":0.842289}
{"client_full_id":"client-job-go-4s-60c-1m-4-zzz8t-42","server_ip":"server-service","server_port":8080,"messages_sent":1,"messages_received":1,"connection_success":true,"total_latency_ms":0.364331,"errors":[],"average_latency_ms":0.364331}
{"client_full_id":"client-job-go-4s-60c-1m-4-zzz8t-28","server_ip":"server-service","server_port":8080,"messages_sent":1,"messages_received":1,"connection_success":true,"total_latency_ms":0.354226,"errors":[],"average_latency_ms":0.354226}
{"client_full_id":"client-job-go-4s-60c-1m-4-zzz8t-20","server_ip":"server-service","server_port":8080,"messages_sent":1,"messages_received":1,"connection_success":true,"total_latency_ms":0.150233,"errors":[],"average_latency_ms":0.150233}
{"client_full_id":"client-job-go-4s-60c-1m-4-zzz8t-36","server_ip":"server-service","server_port":8080,"messages_sent":1,"messages_received":1,"connection_success":true,"total_latency_ms":1.461847,"errors":[],"average_latency_ms":1.461847}
{"client_full_id":"client-job-go-4s-60c-1m-4-zzz8t-58","server_ip":"server-service","server_port":8080,"messages_sent":1,"messages_received":1,"connection_success":true,"total_latency_ms":0.445661,"errors":[],"average_latency_ms":0.445661}
{"client_full_id":"client-job-go-4s-60c-1m-4-zzz8t-9","server_ip":"server-service","server_port":8080,"messages_sent":1,"messages_received":1,"connection_success":true,"total_latency_ms":1.336203,"errors":[],"average_latency_ms":1.336203}
{"client_full_id":"client-job-go-4s-60c-1m-4-zzz8t-37","server_ip":"server-service","server_port":8080,"messages_sent":1,"messages_received":1,"connection_success":true,"total_latency_ms":1.095812,"errors":[],"average_latency_ms":1.095812}
{"client_full_id":"client-job-go-4s-60c-1m-4-zzz8t-55","server_ip":"server-service","server_port":8080,"messages_sent":1,"messages_received":1,"connection_success":true,"total_latency_ms":0.694909,"errors":[],"average_latency_ms":0.694909}
{"client_full_id":"client-job-go-4s-60c-1m-4-zzz8t-34","server_ip":"server-service","server_port":8080,"messages_sent":1,"messages_received":1,"connection_success":true,"total_latency_ms":0.791727,"errors":[],"average_latency_ms":0.791727}
{"client_full_id":"client-job-go-4s-60c-1m-4-zzz8t-4","server_ip":"server-service","server_port":8080,"messages_sent":1,"messages_received":1,"connection_success":true,"total_latency_ms":0.56655,"errors":[],"average_latency_ms":0.56655}
{"client_full_id":"client-job-go-4s-60c-1m-4-zzz8t-2","server_ip":"server-service","server_port":8080,"messages_sent":1,"messages_received":1,"connection_success":true,"total_latency_ms":1.422908,"errors":[],"average_latency_ms":1.422908}
{"client_full_id":"client-job-go-4s-60c-1m-4-zzz8t-3","server_ip":"server-service","server_port":8080,"messages_sent":1,"messages_received":1,"connection_success":true,"total_latency_ms":1.577247,"errors":[],"average_latency_ms":1.577247}
{"client_full_id":"client-job-go-4s-60c-1m-4-zzz8t-31","server_ip":"server-service","server_port":8080,"messages_sent":1,"messages_received":1,"connection_success":true,"total_latency_ms":0.930954,"errors":[],"average_latency_ms":0.930954}
{"client_full_id":"client-job-go-4s-60c-1m-4-zzz8t-38","server_ip":"server-service","server_port":8080,"messages_sent":1,"messages_received":1,"connection_success":true,"total_latency_ms":0.273198,"errors":[],"average_latency_ms":0.273198}
{"client_full_id":"client-job-go-4s-60c-1m-4-zzz8t-41","server_ip":"server-service","server_port":8080,"messages_sent":1,"messages_received":1,"connection_success":true,"total_latency_ms":0.832743,"errors":[],"average_latency_ms":0.832743}
{"client_full_id":"client-job-go-4s-60c-1m-4-zzz8t-11","server_ip":"server-service","server_port":8080,"messages_sent":1,"messages_received":1,"connection_success":true,"total_latency_ms":0.276975,"errors":[],"average_latency_ms":0.276975}
{"client_full_id":"client-job-go-4s-60c-1m-4-zzz8t-48","server_ip":"server-service","server_port":8080,"messages_sent":1,"messages_received":1,"connection_success":true,"total_latency_ms":0.362173,"errors":[],"average_latency_ms":0.362173}
{"client_full_id":"client-job-go-4s-60c-1m-4-zzz8t-50","server_ip":"server-service","server_port":8080,"messages_sent":1,"messages_received":1,"connection_success":true,"total_latency_ms":0.145809,"errors":[],"average_latency_ms":0.145809}
{"client_full_id":"client-job-go-4s-60c-1m-4-zzz8t-22","server_ip":"server-service","server_port":8080,"messages_sent":1,"messages_received":1,"connection_success":true,"total_latency_ms":0.335564,"errors":[],"average_latency_ms":0.335564}
{"client_full_id":"client-job-go-4s-60c-1m-4-zzz8t-49","server_ip":"server-service","server_port":8080,"messages_sent":1,"messages_received":1,"connection_success":true,"total_latency_ms":0.109845,"errors":[],"average_latency_ms":0.109845}
{"client_full_id":"client-job-go-4s-60c-1m-4-zzz8t-51","server_ip":"server-service","server_port":8080,"messages_sent":1,"messages_received":1,"connection_success":true,"total_latency_ms":1.689993,"errors":[],"average_latency_ms":1.689993}
{"client_full_id":"client-job-go-4s-60c-1m-4-zzz8t-24","server_ip":"server-service","server_port":8080,"messages_sent":1,"messages_received":1,"connection_success":true,"total_latency_ms":2.605572,"errors":[],"average_latency_ms":2.605572}
{"client_full_id":"client-job-go-4s-60c-1m-4-zzz8t-17","server_ip":"server-service","server_port":8080,"messages_sent":1,"messages_received":1,"connection_success":true,"total_latency_ms":1.130871,"errors":[],"average_latency_ms":1.130871}
{"client_full_id":"client-job-go-4s-60c-1m-4-zzz8t-53","server_ip":"server-service","server_port":8080,"messages_sent":1,"messages_received":1,"connection_success":true,"total_latency_ms":1.954092,"errors":[],"average_latency_ms":1.954092}
{"client_full_id":"client-job-go-4s-60c-1m-4-zzz8t-40","server_ip":"server-service","server_port":8080,"messages_sent":1,"messages_received":1,"connection_success":true,"total_latency_ms":2.171045,"errors":[],"average_latency_ms":2.171045}
{"client_full_id":"client-job-go-4s-60c-1m-4-zzz8t-35","server_ip":"server-service","server_port":8080,"messages_sent":1,"messages_received":1,"connection_success":true,"total_latency_ms":0.260019,"errors":[],"average_latency_ms":0.260019}
{"client_full_id":"client-job-go-4s-60c-1m-4-zzz8t-21","server_ip":"server-service","server_port":8080,"messages_sent":1,"messages_received":1,"connection_success":true,"total_latency_ms":0.277413,"errors":[],"average_latency_ms":0.277413}
{"client_full_id":"client-job-go-4s-60c-1m-4-zzz8t-26","server_ip":"server-service","server_port":8080,"messages_sent":1,"messages_received":1,"connection_success":true,"total_latency_ms":0.274655,"errors":[],"average_latency_ms":0.274655}
{"client_full_id":"client-job-go-4s-60c-1m-4-zzz8t-29","server_ip":"server-service","server_port":8080,"messages_sent":1,"messages_received":1,"connection_success":true,"total_latency_ms":2.687159,"errors":[],"average_latency_ms":2.687159}
{"client_full_id":"client-job-go-4s-60c-1m-4-zzz8t-33","server_ip":"server-service","server_port":8080,"messages_sent":1,"messages_received":1,"connection_success":true,"total_latency_ms":2.712007,"errors":[],"average_latency_ms":2.712007}
{"client_full_id":"client-job-go-4s-60c-1m-4-zzz8t-45","server_ip":"server-service","server_port":8080,"messages_sent":1,"messages_received":1,"connection_success":true,"total_latency_ms":3.153747,"errors":[],"average_latency_ms":3.153747}
{"client_full_id":"client-job-go-4s-60c-1m-4-zzz8t-25","server_ip":"server-service","server_port":8080,"messages_sent":1,"messages_received":1,"connection_success":true,"total_latency_ms":0.383776,"errors":[],"average_latency_ms":0.383776}
{"client_full_id":"client-job-go-4s-60c-1m-4-zzz8t-0","server_ip":"server-service","server_port":8080,"messages_sent":1,"messages_received":1,"connection_success":true,"total_latency_ms":2.690063,"errors":[],"average_latency_ms":2.690063}
{"client_full_id":"client-job-go-4s-60c-1m-4-zzz8t-30","server_ip":"server-service","server_port":8080,"messages_sent":1,"messages_received":1,"connection_success":true,"total_latency_ms":1.351115,"errors":[],"average_latency_ms":1.351115}
{"client_full_id":"client-job-go-4s-60c-1m-4-zzz8t-16","server_ip":"server-service","server_port":8080,"messages_sent":1,"messages_received":1,"connection_success":true,"total_latency_ms":0.318059,"errors":[],"average_latency_ms":0.318059}
{"client_full_id":"client-job-go-4s-60c-1m-4-zzz8t-23","server_ip":"server-service","server_port":8080,"messages_sent":1,"messages_received":1,"connection_success":true,"total_latency_ms":1.963581,"errors":[],"average_latency_ms":1.963581}
{"client_full_id":"client-job-go-4s-60c-1m-4-zzz8t-27","server_ip":"server-service","server_port":8080,"messages_sent":1,"messages_received":1,"connection_success":true,"total_latency_ms":2.661586,"errors":[],"average_latency_ms":2.661586}
{"client_full_id":"client-job-go-4s-60c-1m-4-zzz8t-5","server_ip":"server-service","server_port":8080,"messages_sent":1,"messages_received":1,"connection_success":true,"total_latency_ms":2.25235,"errors":[],"average_latency_ms":2.25235}
{"client_full_id":"client-job-go-4s-60c-1m-4-zzz8t-32","server_ip":"server-service","server_port":8080,"messages_sent":1,"messages_received":1,"connection_success":true,"total_latency_ms":1.95295,"errors":[],"average_latency_ms":1.95295}
{"client_full_id":"client-job-go-4s-60c-1m-4-zzz8t-14","server_ip":"server-service","server_port":8080,"messages_sent":1,"messages_received":1,"connection_success":true,"total_latency_ms":0.147308,"errors":[],"average_latency_ms":0.147308}
{"client_full_id":"client-job-go-4s-60c-1m-4-zzz8t-18","server_ip":"server-service","server_port":8080,"messages_sent":1,"messages_received":1,"connection_success":true,"total_latency_ms":0.276917,"errors":[],"average_latency_ms":0.276917}
{"client_full_id":"client-job-go-4s-60c-1m-4-zzz8t-43","server_ip":"server-service","server_port":8080,"messages_sent":1,"messages_received":1,"connection_success":true,"total_latency_ms":1.899789,"errors":[],"average_latency_ms":1.899789}
{"client_full_id":"client-job-go-4s-60c-1m-4-zzz8t-52","server_ip":"server-service","server_port":8080,"messages_sent":1,"messages_received":1,"connection_success":true,"total_latency_ms":2.471668,"errors":[],"average_latency_ms":2.471668}
{"client_full_id":"client-job-go-4s-60c-1m-4-zzz8t-54","server_ip":"server-service","server_port":8080,"messages_sent":1,"messages_received":1,"connection_success":true,"total_latency_ms":1.521052,"errors":[],"average_latency_ms":1.521052}
{"client_full_id":"client-job-go-4s-60c-1m-4-zzz8t-12","server_ip":"server-service","server_port":8080,"messages_sent":1,"messages_received":1,"connection_success":true,"total_latency_ms":2.108906,"errors":[],"average_latency_ms":2.108906}
{"client_full_id":"client-job-go-4s-60c-1m-4-zzz8t-56","server_ip":"server-service","server_port":8080,"messages_sent":1,"messages_received":1,"connection_success":true,"total_latency_ms":3.052863,"errors":[],"average_latency_ms":3.052863}
{"client_full_id":"client-job-go-4s-60c-1m-4-zzz8t-57","server_ip":"server-service","server_port":8080,"messages_sent":1,"messages_received":1,"connection_success":true,"total_latency_ms":2.362072,"errors":[],"average_latency_ms":2.362072}
{"client_full_id":"client-job-go-4s-60c-1m-4-zzz8t-8","server_ip":"server-service","server_port":8080,"messages_sent":1,"messages_received":1,"connection_success":true,"total_latency_ms":0.275505,"errors":[],"average_latency_ms":0.275505}
{"client_full_id":"client-job-go-4s-60c-1m-4-zzz8t-46","server_ip":"server-service","server_port":8080,"messages_sent":1,"messages_received":1,"connection_success":true,"total_latency_ms":1.154435,"errors":[],"average_latency_ms":1.154435}
{"client_full_id":"client-job-go-4s-60c-1m-4-zzz8t-7","server_ip":"server-service","server_port":8080,"messages_sent":1,"messages_received":1,"connection_success":true,"total_latency_ms":0.137243,"errors":[],"average_latency_ms":0.137243}
{"client_full_id":"client-job-go-4s-60c-1m-4-zzz8t-19","server_ip":"server-service","server_port":8080,"messages_sent":1,"messages_received":1,"connection_success":true,"total_latency_ms":0.411276,"errors":[],"average_latency_ms":0.411276}
{"client_full_id":"client-job-go-4s-60c-1m-4-zzz8t-44","server_ip":"server-service","server_port":8080,"messages_sent":1,"messages_received":1,"connection_success":true,"total_latency_ms":0.633862,"errors":[],"average_latency_ms":0.633862}
{"client_full_id":"client-job-go-4s-60c-1m-4-zzz8t-6","server_ip":"server-service","server_port":8080,"messages_sent":1,"messages_received":1,"connection_success":true,"total_latency_ms":0.517968,"errors":[],"average_latency_ms":0.517968}
{"client_full_id":"client-job-go-4s-60c-1m-4-zzz8t-1","server_ip":"server-service","server_port":8080,"messages_sent":1,"messages_received":1,"connection_success":true,"total_latency_ms":0.092415,"errors":[],"average_latency_ms":0.092415}
{"client_full_id":"client-job-go-4s-60c-1m-4-zzz8t-59","server_ip":"server-service","server_port":8080,"messages_sent":1,"messages_received":1,"connection_success":true,"total_latency_ms":0.54131,"errors":[],"average_latency_ms":0.54131}
{"client_full_id":"client-job-go-4s-60c-1m-4-zzz8t-47","server_ip":"server-service","server_port":8080,"messages_sent":1,"messages_received":1,"connection_success":true,"total_latency_ms":2.705885,"errors":[],"average_latency_ms":2.705885}
