{"client_full_id":"client-job-go-10s-10c-10000m-1-mw6bs-7","server_ip":"server-service","server_port":8080,"messages_sent":10000,"messages_received":10000,"connection_success":true,"total_latency_ms":3810.735165000024,"errors":[],"average_latency_ms":0.38107351650000243}
{"client_full_id":"client-job-go-10s-10c-10000m-1-mw6bs-8","server_ip":"server-service","server_port":8080,"messages_sent":10000,"messages_received":10000,"connection_success":true,"total_latency_ms":3950.2190489999816,"errors":[],"average_latency_ms":0.39502190489999817}
{"client_full_id":"client-job-go-10s-10c-10000m-1-mw6bs-0","server_ip":"server-service","server_port":8080,"messages_sent":10000,"messages_received":10000,"connection_success":true,"total_latency_ms":3955.542132000002,"errors":[],"average_latency_ms":0.39555421320000017}
{"client_full_id":"client-job-go-10s-10c-10000m-1-mw6bs-4","server_ip":"server-service","server_port":8080,"messages_sent":10000,"messages_received":10000,"connection_success":true,"total_latency_ms":3974.304161000005,"errors":[],"average_latency_ms":0.3974304161000005}
{"client_full_id":"client-job-go-10s-10c-10000m-1-mw6bs-9","server_ip":"server-service","server_port":8080,"messages_sent":10000,"messages_received":10000,"connection_success":true,"total_latency_ms":3971.570927000004,"errors":[],"average_latency_ms":0.3971570927000004}
{"client_full_id":"client-job-go-10s-10c-10000m-1-mw6bs-1","server_ip":"server-service","server_port":8080,"messages_sent":10000,"messages_received":10000,"connection_success":true,"total_latency_ms":3975.6248380000166,"errors":[],"average_latency_ms":0.39756248380000164}
{"client_full_id":"client-job-go-10s-10c-10000m-1-mw6bs-6","server_ip":"server-service","server_port":8080,"messages_sent":10000,"messages_received":10000,"connection_success":true,"total_latency_ms":3971.8959640000066,"errors":[],"average_latency_ms":0.3971895964000007}
{"client_full_id":"client-job-go-10s-10c-10000m-1-mw6bs-3","server_ip":"server-service","server_port":8080,"messages_sent":10000,"messages_received":10000,"connection_success":true,"total_latency_ms":4018.8167500000095,"errors":[],"average_latency_ms":0.40188167500000094}
{"client_full_id":"client-job-go-10s-10c-10000m-1-mw6bs-5","server_ip":"server-service","server_port":8080,"messages_sent":10000,"messages_received":10000,"connection_success":true,"total_latency_ms":4022.814488000004,"errors":[],"average_latency_ms":0.4022814488000004}
{"client_full_id":"client-job-go-10s-10c-10000m-1-mw6bs-2","server_ip":"server-service","server_port":8080,"messages_sent":10000,"messages_received":10000,"connection_success":true,"total_latency_ms":4019.6805740000027,"errors":[],"average_latency_ms":0.40196805740000024}
