{"client_full_id":"client-job-go-8s-100c-10000m-5-xx65c-34","server_ip":"server-service","server_port":8080,"messages_sent":10000,"messages_received":10000,"connection_success":true,"total_latency_ms":14266.454263000052,"errors":[],"average_latency_ms":1.4266454263000052}
{"client_full_id":"client-job-go-8s-100c-10000m-5-xx65c-76","server_ip":"server-service","server_port":8080,"messages_sent":10000,"messages_received":10000,"connection_success":true,"total_latency_ms":14267.538526999975,"errors":[],"average_latency_ms":1.4267538526999974}
{"client_full_id":"client-job-go-8s-100c-10000m-5-xx65c-17","server_ip":"server-service","server_port":8080,"messages_sent":10000,"messages_received":10000,"connection_success":true,"total_latency_ms":14358.078676000037,"errors":[],"average_latency_ms":1.4358078676000037}
{"client_full_id":"client-job-go-8s-100c-10000m-5-xx65c-20","server_ip":"server-service","server_port":8080,"messages_sent":10000,"messages_received":10000,"connection_success":true,"total_latency_ms":14430.708924999999,"errors":[],"average_latency_ms":1.4430708925}
{"client_full_id":"client-job-go-8s-100c-10000m-5-xx65c-42","server_ip":"server-service","server_port":8080,"messages_sent":10000,"messages_received":10000,"connection_success":true,"total_latency_ms":14443.672439999982,"errors":[],"average_latency_ms":1.4443672439999982}
{"client_full_id":"client-job-go-8s-100c-10000m-5-xx65c-3","server_ip":"server-service","server_port":8080,"messages_sent":10000,"messages_received":10000,"connection_success":true,"total_latency_ms":14441.509086000022,"errors":[],"average_latency_ms":1.4441509086000022}
{"client_full_id":"client-job-go-8s-100c-10000m-5-xx65c-65","server_ip":"server-service","server_port":8080,"messages_sent":10000,"messages_received":10000,"connection_success":true,"total_latency_ms":14480.02390000001,"errors":[],"average_latency_ms":1.448002390000001}
{"client_full_id":"client-job-go-8s-100c-10000m-5-xx65c-18","server_ip":"server-service","server_port":8080,"messages_sent":10000,"messages_received":10000,"connection_success":true,"total_latency_ms":14506.017087999995,"errors":[],"average_latency_ms":1.4506017087999996}
{"client_full_id":"client-job-go-8s-100c-10000m-5-xx65c-87","server_ip":"server-service","server_port":8080,"messages_sent":10000,"messages_received":10000,"connection_success":true,"total_latency_ms":14599.125144000065,"errors":[],"average_latency_ms":1.4599125144000065}
{"client_full_id":"client-job-go-8s-100c-10000m-5-xx65c-97","server_ip":"server-service","server_port":8080,"messages_sent":10000,"messages_received":10000,"connection_success":true,"total_latency_ms":14795.852666999992,"errors":[],"average_latency_ms":1.4795852666999991}
{"client_full_id":"client-job-go-8s-100c-10000m-5-xx65c-54","server_ip":"server-service","server_port":8080,"messages_sent":10000,"messages_received":10000,"connection_success":true,"total_latency_ms":14910.266187999952,"errors":[],"average_latency_ms":1.4910266187999952}
{"client_full_id":"client-job-go-8s-100c-10000m-5-xx65c-22","server_ip":"server-service","server_port":8080,"messages_sent":10000,"messages_received":10000,"connection_success":true,"total_latency_ms":14851.424142000003,"errors":[],"average_latency_ms":1.4851424142000003}
{"client_full_id":"client-job-go-8s-100c-10000m-5-xx65c-29","server_ip":"server-service","server_port":8080,"messages_sent":10000,"messages_received":10000,"connection_success":true,"total_latency_ms":14962.457526999971,"errors":[],"average_latency_ms":1.496245752699997}
{"client_full_id":"client-job-go-8s-100c-10000m-5-xx65c-74","server_ip":"server-service","server_port":8080,"messages_sent":10000,"messages_received":10000,"connection_success":true,"total_latency_ms":14964.483674000014,"errors":[],"average_latency_ms":1.4964483674000013}
{"client_full_id":"client-job-go-8s-100c-10000m-5-xx65c-37","server_ip":"server-service","server_port":8080,"messages_sent":10000,"messages_received":10000,"connection_success":true,"total_latency_ms":14997.737178000008,"errors":[],"average_latency_ms":1.4997737178000008}
{"client_full_id":"client-job-go-8s-100c-10000m-5-xx65c-19","server_ip":"server-service","server_port":8080,"messages_sent":10000,"messages_received":10000,"connection_success":true,"total_latency_ms":14914.775882000014,"errors":[],"average_latency_ms":1.4914775882000015}
{"client_full_id":"client-job-go-8s-100c-10000m-5-xx65c-53","server_ip":"server-service","server_port":8080,"messages_sent":10000,"messages_received":10000,"connection_success":true,"total_latency_ms":15042.376548000007,"errors":[],"average_latency_ms":1.5042376548000007}
{"client_full_id":"client-job-go-8s-100c-10000m-5-xx65c-41","server_ip":"server-service","server_port":8080,"messages_sent":10000,"messages_received":10000,"connection_success":true,"total_latency_ms":15230.576197000057,"errors":[],"average_latency_ms":1.5230576197000056}
{"client_full_id":"client-job-go-8s-100c-10000m-5-xx65c-45","server_ip":"server-service","server_port":8080,"messages_sent":10000,"messages_received":10000,"connection_success":true,"total_latency_ms":15088.269431999975,"errors":[],"average_latency_ms":1.5088269431999974}
{"client_full_id":"client-job-go-8s-100c-10000m-5-xx65c-57","server_ip":"server-service","server_port":8080,"messages_sent":10000,"messages_received":10000,"connection_success":true,"total_latency_ms":15101.002588999963,"errors":[],"average_latency_ms":1.5101002588999963}
{"client_full_id":"client-job-go-8s-100c-10000m-5-xx65c-58","server_ip":"server-service","server_port":8080,"messages_sent":10000,"messages_received":10000,"connection_success":true,"total_latency_ms":15087.28006199998,"errors":[],"average_latency_ms":1.508728006199998}
{"client_full_id":"client-job-go-8s-100c-10000m-5-xx65c-82","server_ip":"server-service","server_port":8080,"messages_sent":10000,"messages_received":10000,"connection_success":true,"total_latency_ms":15178.576185999967,"errors":[],"average_latency_ms":1.5178576185999968}
{"client_full_id":"client-job-go-8s-100c-10000m-5-xx65c-33","server_ip":"server-service","server_port":8080,"messages_sent":10000,"messages_received":10000,"connection_success":true,"total_latency_ms":15095.625940999971,"errors":[],"average_latency_ms":1.509562594099997}
{"client_full_id":"client-job-go-8s-100c-10000m-5-xx65c-28","server_ip":"server-service","server_port":8080,"messages_sent":10000,"messages_received":10000,"connection_success":true,"total_latency_ms":15003.928393999973,"errors":[],"average_latency_ms":1.5003928393999972}
{"client_full_id":"client-job-go-8s-100c-10000m-5-xx65c-7","server_ip":"server-service","server_port":8080,"messages_sent":10000,"messages_received":10000,"connection_success":true,"total_latency_ms":15108.150336999992,"errors":[],"average_latency_ms":1.5108150336999993}
{"client_full_id":"client-job-go-8s-100c-10000m-5-xx65c-10","server_ip":"server-service","server_port":8080,"messages_sent":10000,"messages_received":10000,"connection_success":true,"total_latency_ms":15122.83771600001,"errors":[],"average_latency_ms":1.5122837716000008}
{"client_full_id":"client-job-go-8s-100c-10000m-5-xx65c-88","server_ip":"server-service","server_port":8080,"messages_sent":10000,"messages_received":10000,"connection_success":true,"total_latency_ms":15102.734771000014,"errors":[],"average_latency_ms":1.5102734771000015}
{"client_full_id":"client-job-go-8s-100c-10000m-5-xx65c-72","server_ip":"server-service","server_port":8080,"messages_sent":10000,"messages_received":10000,"connection_success":true,"total_latency_ms":15146.747199999965,"errors":[],"average_latency_ms":1.5146747199999966}
{"client_full_id":"client-job-go-8s-100c-10000m-5-xx65c-86","server_ip":"server-service","server_port":8080,"messages_sent":10000,"messages_received":10000,"connection_success":true,"total_latency_ms":15218.534603000015,"errors":[],"average_latency_ms":1.5218534603000016}
{"client_full_id":"client-job-go-8s-100c-10000m-5-xx65c-84","server_ip":"server-service","server_port":8080,"messages_sent":10000,"messages_received":10000,"connection_success":true,"total_latency_ms":15168.965293999983,"errors":[],"average_latency_ms":1.5168965293999983}
{"client_full_id":"client-job-go-8s-100c-10000m-5-xx65c-71","server_ip":"server-service","server_port":8080,"messages_sent":10000,"messages_received":10000,"connection_success":true,"total_latency_ms":15315.05202800004,"errors":[],"average_latency_ms":1.531505202800004}
{"client_full_id":"client-job-go-8s-100c-10000m-5-xx65c-15","server_ip":"server-service","server_port":8080,"messages_sent":10000,"messages_received":10000,"connection_success":true,"total_latency_ms":15271.803939999993,"errors":[],"average_latency_ms":1.5271803939999993}
{"client_full_id":"client-job-go-8s-100c-10000m-5-xx65c-50","server_ip":"server-service","server_port":8080,"messages_sent":10000,"messages_received":10000,"connection_success":true,"total_latency_ms":15228.576342999935,"errors":[],"average_latency_ms":1.5228576342999935}
{"client_full_id":"client-job-go-8s-100c-10000m-5-xx65c-31","server_ip":"server-service","server_port":8080,"messages_sent":10000,"messages_received":10000,"connection_success":true,"total_latency_ms":15260.491813000011,"errors":[],"average_latency_ms":1.5260491813000012}
{"client_full_id":"client-job-go-8s-100c-10000m-5-xx65c-83","server_ip":"server-service","server_port":8080,"messages_sent":10000,"messages_received":10000,"connection_success":true,"total_latency_ms":15383.213505999987,"errors":[],"average_latency_ms":1.5383213505999986}
{"client_full_id":"client-job-go-8s-100c-10000m-5-xx65c-12","server_ip":"server-service","server_port":8080,"messages_sent":10000,"messages_received":10000,"connection_success":true,"total_latency_ms":15333.786711999974,"errors":[],"average_latency_ms":1.5333786711999973}
{"client_full_id":"client-job-go-8s-100c-10000m-5-xx65c-75","server_ip":"server-service","server_port":8080,"messages_sent":10000,"messages_received":10000,"connection_success":true,"total_latency_ms":15411.923239999953,"errors":[],"average_latency_ms":1.5411923239999952}
{"client_full_id":"client-job-go-8s-100c-10000m-5-xx65c-93","server_ip":"server-service","server_port":8080,"messages_sent":10000,"messages_received":10000,"connection_success":true,"total_latency_ms":15348.83842699997,"errors":[],"average_latency_ms":1.534883842699997}
{"client_full_id":"client-job-go-8s-100c-10000m-5-xx65c-13","server_ip":"server-service","server_port":8080,"messages_sent":10000,"messages_received":10000,"connection_success":true,"total_latency_ms":15355.457047000002,"errors":[],"average_latency_ms":1.5355457047}
{"client_full_id":"client-job-go-8s-100c-10000m-5-xx65c-81","server_ip":"server-service","server_port":8080,"messages_sent":10000,"messages_received":10000,"connection_success":true,"total_latency_ms":15417.957270000037,"errors":[],"average_latency_ms":1.5417957270000038}
{"client_full_id":"client-job-go-8s-100c-10000m-5-xx65c-63","server_ip":"server-service","server_port":8080,"messages_sent":10000,"messages_received":10000,"connection_success":true,"total_latency_ms":15371.170746000016,"errors":[],"average_latency_ms":1.5371170746000016}
{"client_full_id":"client-job-go-8s-100c-10000m-5-xx65c-99","server_ip":"server-service","server_port":8080,"messages_sent":10000,"messages_received":10000,"connection_success":true,"total_latency_ms":15461.081562999978,"errors":[],"average_latency_ms":1.5461081562999979}
{"client_full_id":"client-job-go-8s-100c-10000m-5-xx65c-85","server_ip":"server-service","server_port":8080,"messages_sent":10000,"messages_received":10000,"connection_success":true,"total_latency_ms":15389.70935299997,"errors":[],"average_latency_ms":1.538970935299997}
{"client_full_id":"client-job-go-8s-100c-10000m-5-xx65c-32","server_ip":"server-service","server_port":8080,"messages_sent":10000,"messages_received":10000,"connection_success":true,"total_latency_ms":15387.26884300007,"errors":[],"average_latency_ms":1.538726884300007}
{"client_full_id":"client-job-go-8s-100c-10000m-5-xx65c-46","server_ip":"server-service","server_port":8080,"messages_sent":10000,"messages_received":10000,"connection_success":true,"total_latency_ms":15281.613157000056,"errors":[],"average_latency_ms":1.5281613157000056}
{"client_full_id":"client-job-go-8s-100c-10000m-5-xx65c-39","server_ip":"server-service","server_port":8080,"messages_sent":10000,"messages_received":10000,"connection_success":true,"total_latency_ms":15408.149132000017,"errors":[],"average_latency_ms":1.5408149132000017}
{"client_full_id":"client-job-go-8s-100c-10000m-5-xx65c-96","server_ip":"server-service","server_port":8080,"messages_sent":10000,"messages_received":10000,"connection_success":true,"total_latency_ms":15407.21213299994,"errors":[],"average_latency_ms":1.5407212132999941}
{"client_full_id":"client-job-go-8s-100c-10000m-5-xx65c-62","server_ip":"server-service","server_port":8080,"messages_sent":10000,"messages_received":10000,"connection_success":true,"total_latency_ms":15419.977795999945,"errors":[],"average_latency_ms":1.5419977795999944}
{"client_full_id":"client-job-go-8s-100c-10000m-5-xx65c-61","server_ip":"server-service","server_port":8080,"messages_sent":10000,"messages_received":10000,"connection_success":true,"total_latency_ms":15365.820890999941,"errors":[],"average_latency_ms":1.5365820890999942}
{"client_full_id":"client-job-go-8s-100c-10000m-5-xx65c-79","server_ip":"server-service","server_port":8080,"messages_sent":10000,"messages_received":10000,"connection_success":true,"total_latency_ms":15348.414847000018,"errors":[],"average_latency_ms":1.5348414847000018}
{"client_full_id":"client-job-go-8s-100c-10000m-5-xx65c-90","server_ip":"server-service","server_port":8080,"messages_sent":10000,"messages_received":10000,"connection_success":true,"total_latency_ms":15430.313677999995,"errors":[],"average_latency_ms":1.5430313677999994}
{"client_full_id":"client-job-go-8s-100c-10000m-5-xx65c-51","server_ip":"server-service","server_port":8080,"messages_sent":10000,"messages_received":10000,"connection_success":true,"total_latency_ms":15497.971390999965,"errors":[],"average_latency_ms":1.5497971390999965}
{"client_full_id":"client-job-go-8s-100c-10000m-5-xx65c-6","server_ip":"server-service","server_port":8080,"messages_sent":10000,"messages_received":10000,"connection_success":true,"total_latency_ms":15450.172532999995,"errors":[],"average_latency_ms":1.5450172532999995}
{"client_full_id":"client-job-go-8s-100c-10000m-5-xx65c-78","server_ip":"server-service","server_port":8080,"messages_sent":10000,"messages_received":10000,"connection_success":true,"total_latency_ms":15456.378022999994,"errors":[],"average_latency_ms":1.5456378022999995}
{"client_full_id":"client-job-go-8s-100c-10000m-5-xx65c-9","server_ip":"server-service","server_port":8080,"messages_sent":10000,"messages_received":10000,"connection_success":true,"total_latency_ms":15411.647809999959,"errors":[],"average_latency_ms":1.5411647809999958}
{"client_full_id":"client-job-go-8s-100c-10000m-5-xx65c-64","server_ip":"server-service","server_port":8080,"messages_sent":10000,"messages_received":10000,"connection_success":true,"total_latency_ms":15459.873107000041,"errors":[],"average_latency_ms":1.5459873107000042}
{"client_full_id":"client-job-go-8s-100c-10000m-5-xx65c-47","server_ip":"server-service","server_port":8080,"messages_sent":10000,"messages_received":10000,"connection_success":true,"total_latency_ms":15451.434380000004,"errors":[],"average_latency_ms":1.5451434380000004}
{"client_full_id":"client-job-go-8s-100c-10000m-5-xx65c-40","server_ip":"server-service","server_port":8080,"messages_sent":10000,"messages_received":10000,"connection_success":true,"total_latency_ms":15473.214561000046,"errors":[],"average_latency_ms":1.5473214561000046}
{"client_full_id":"client-job-go-8s-100c-10000m-5-xx65c-25","server_ip":"server-service","server_port":8080,"messages_sent":10000,"messages_received":10000,"connection_success":true,"total_latency_ms":15423.316449000002,"errors":[],"average_latency_ms":1.5423316449000002}
{"client_full_id":"client-job-go-8s-100c-10000m-5-xx65c-1","server_ip":"server-service","server_port":8080,"messages_sent":10000,"messages_received":10000,"connection_success":true,"total_latency_ms":15461.641168999955,"errors":[],"average_latency_ms":1.5461641168999956}
{"client_full_id":"client-job-go-8s-100c-10000m-5-xx65c-11","server_ip":"server-service","server_port":8080,"messages_sent":10000,"messages_received":10000,"connection_success":true,"total_latency_ms":15463.439072999941,"errors":[],"average_latency_ms":1.546343907299994}
{"client_full_id":"client-job-go-8s-100c-10000m-5-xx65c-60","server_ip":"server-service","server_port":8080,"messages_sent":10000,"messages_received":10000,"connection_success":true,"total_latency_ms":15546.904713000094,"errors":[],"average_latency_ms":1.5546904713000094}
{"client_full_id":"client-job-go-8s-100c-10000m-5-xx65c-94","server_ip":"server-service","server_port":8080,"messages_sent":10000,"messages_received":10000,"connection_success":true,"total_latency_ms":15436.298563000015,"errors":[],"average_latency_ms":1.5436298563000015}
{"client_full_id":"client-job-go-8s-100c-10000m-5-xx65c-77","server_ip":"server-service","server_port":8080,"messages_sent":10000,"messages_received":10000,"connection_success":true,"total_latency_ms":15411.538659000049,"errors":[],"average_latency_ms":1.5411538659000048}
{"client_full_id":"client-job-go-8s-100c-10000m-5-xx65c-55","server_ip":"server-service","server_port":8080,"messages_sent":10000,"messages_received":10000,"connection_success":true,"total_latency_ms":15512.256942999966,"errors":[],"average_latency_ms":1.5512256942999967}
{"client_full_id":"client-job-go-8s-100c-10000m-5-xx65c-23","server_ip":"server-service","server_port":8080,"messages_sent":10000,"messages_received":10000,"connection_success":true,"total_latency_ms":15552.353441000023,"errors":[],"average_latency_ms":1.5552353441000022}
{"client_full_id":"client-job-go-8s-100c-10000m-5-xx65c-80","server_ip":"server-service","server_port":8080,"messages_sent":10000,"messages_received":10000,"connection_success":true,"total_latency_ms":15481.316705000007,"errors":[],"average_latency_ms":1.5481316705000006}
{"client_full_id":"client-job-go-8s-100c-10000m-5-xx65c-5","server_ip":"server-service","server_port":8080,"messages_sent":10000,"messages_received":10000,"connection_success":true,"total_latency_ms":15527.926744000013,"errors":[],"average_latency_ms":1.5527926744000013}
{"client_full_id":"client-job-go-8s-100c-10000m-5-xx65c-98","server_ip":"server-service","server_port":8080,"messages_sent":10000,"messages_received":10000,"connection_success":true,"total_latency_ms":15459.809539999933,"errors":[],"average_latency_ms":1.5459809539999934}
{"client_full_id":"client-job-go-8s-100c-10000m-5-xx65c-70","server_ip":"server-service","server_port":8080,"messages_sent":10000,"messages_received":10000,"connection_success":true,"total_latency_ms":15491.683060999994,"errors":[],"average_latency_ms":1.5491683060999994}
{"client_full_id":"client-job-go-8s-100c-10000m-5-xx65c-21","server_ip":"server-service","server_port":8080,"messages_sent":10000,"messages_received":10000,"connection_success":true,"total_latency_ms":15569.380835000009,"errors":[],"average_latency_ms":1.5569380835000008}
{"client_full_id":"client-job-go-8s-100c-10000m-5-xx65c-38","server_ip":"server-service","server_port":8080,"messages_sent":10000,"messages_received":10000,"connection_success":true,"total_latency_ms":15544.530538000045,"errors":[],"average_latency_ms":1.5544530538000045}
{"client_full_id":"client-job-go-8s-100c-10000m-5-xx65c-27","server_ip":"server-service","server_port":8080,"messages_sent":10000,"messages_received":10000,"connection_success":true,"total_latency_ms":15506.895480000077,"errors":[],"average_latency_ms":1.5506895480000078}
{"client_full_id":"client-job-go-8s-100c-10000m-5-xx65c-67","server_ip":"server-service","server_port":8080,"messages_sent":10000,"messages_received":10000,"connection_success":true,"total_latency_ms":15551.86811799997,"errors":[],"average_latency_ms":1.555186811799997}
{"client_full_id":"client-job-go-8s-100c-10000m-5-xx65c-91","server_ip":"server-service","server_port":8080,"messages_sent":10000,"messages_received":10000,"connection_success":true,"total_latency_ms":15577.088804000026,"errors":[],"average_latency_ms":1.5577088804000025}
{"client_full_id":"client-job-go-8s-100c-10000m-5-xx65c-4","server_ip":"server-service","server_port":8080,"messages_sent":10000,"messages_received":10000,"connection_success":true,"total_latency_ms":15514.288582000003,"errors":[],"average_latency_ms":1.5514288582000002}
{"client_full_id":"client-job-go-8s-100c-10000m-5-xx65c-8","server_ip":"server-service","server_port":8080,"messages_sent":10000,"messages_received":10000,"connection_success":true,"total_latency_ms":15505.189211000028,"errors":[],"average_latency_ms":1.5505189211000028}
{"client_full_id":"client-job-go-8s-100c-10000m-5-xx65c-44","server_ip":"server-service","server_port":8080,"messages_sent":10000,"messages_received":10000,"connection_success":true,"total_latency_ms":15575.50494599997,"errors":[],"average_latency_ms":1.557550494599997}
{"client_full_id":"client-job-go-8s-100c-10000m-5-xx65c-66","server_ip":"server-service","server_port":8080,"messages_sent":10000,"messages_received":10000,"connection_success":true,"total_latency_ms":15430.295634000042,"errors":[],"average_latency_ms":1.5430295634000042}
{"client_full_id":"client-job-go-8s-100c-10000m-5-xx65c-89","server_ip":"server-service","server_port":8080,"messages_sent":10000,"messages_received":10000,"connection_success":true,"total_latency_ms":15552.968443999927,"errors":[],"average_latency_ms":1.5552968443999928}
{"client_full_id":"client-job-go-8s-100c-10000m-5-xx65c-48","server_ip":"server-service","server_port":8080,"messages_sent":10000,"messages_received":10000,"connection_success":true,"total_latency_ms":15610.36625999999,"errors":[],"average_latency_ms":1.561036625999999}
{"client_full_id":"client-job-go-8s-100c-10000m-5-xx65c-56","server_ip":"server-service","server_port":8080,"messages_sent":10000,"messages_received":10000,"connection_success":true,"total_latency_ms":15550.231656000042,"errors":[],"average_latency_ms":1.5550231656000042}
{"client_full_id":"client-job-go-8s-100c-10000m-5-xx65c-95","server_ip":"server-service","server_port":8080,"messages_sent":10000,"messages_received":10000,"connection_success":true,"total_latency_ms":15527.839551999981,"errors":[],"average_latency_ms":1.5527839551999982}
{"client_full_id":"client-job-go-8s-100c-10000m-5-xx65c-36","server_ip":"server-service","server_port":8080,"messages_sent":10000,"messages_received":10000,"connection_success":true,"total_latency_ms":15557.725353999982,"errors":[],"average_latency_ms":1.5557725353999983}
{"client_full_id":"client-job-go-8s-100c-10000m-5-xx65c-73","server_ip":"server-service","server_port":8080,"messages_sent":10000,"messages_received":10000,"connection_success":true,"total_latency_ms":15646.342396000027,"errors":[],"average_latency_ms":1.5646342396000028}
{"client_full_id":"client-job-go-8s-100c-10000m-5-xx65c-30","server_ip":"server-service","server_port":8080,"messages_sent":10000,"messages_received":10000,"connection_success":true,"total_latency_ms":15623.323046999989,"errors":[],"average_latency_ms":1.5623323046999988}
{"client_full_id":"client-job-go-8s-100c-10000m-5-xx65c-52","server_ip":"server-service","server_port":8080,"messages_sent":10000,"messages_received":10000,"connection_success":true,"total_latency_ms":15642.983570999986,"errors":[],"average_latency_ms":1.5642983570999986}
{"client_full_id":"client-job-go-8s-100c-10000m-5-xx65c-14","server_ip":"server-service","server_port":8080,"messages_sent":10000,"messages_received":10000,"connection_success":true,"total_latency_ms":15640.726289999926,"errors":[],"average_latency_ms":1.5640726289999927}
{"client_full_id":"client-job-go-8s-100c-10000m-5-xx65c-16","server_ip":"server-service","server_port":8080,"messages_sent":10000,"messages_received":10000,"connection_success":true,"total_latency_ms":15602.304129999957,"errors":[],"average_latency_ms":1.5602304129999958}
{"client_full_id":"client-job-go-8s-100c-10000m-5-xx65c-2","server_ip":"server-service","server_port":8080,"messages_sent":10000,"messages_received":10000,"connection_success":true,"total_latency_ms":15624.453287999999,"errors":[],"average_latency_ms":1.5624453288}
{"client_full_id":"client-job-go-8s-100c-10000m-5-xx65c-26","server_ip":"server-service","server_port":8080,"messages_sent":10000,"messages_received":10000,"connection_success":true,"total_latency_ms":15623.934501,"errors":[],"average_latency_ms":1.5623934501}
{"client_full_id":"client-job-go-8s-100c-10000m-5-xx65c-24","server_ip":"server-service","server_port":8080,"messages_sent":10000,"messages_received":10000,"connection_success":true,"total_latency_ms":15610.56031900005,"errors":[],"average_latency_ms":1.5610560319000049}
{"client_full_id":"client-job-go-8s-100c-10000m-5-xx65c-69","server_ip":"server-service","server_port":8080,"messages_sent":10000,"messages_received":10000,"connection_success":true,"total_latency_ms":15684.77516199998,"errors":[],"average_latency_ms":1.568477516199998}
{"client_full_id":"client-job-go-8s-100c-10000m-5-xx65c-92","server_ip":"server-service","server_port":8080,"messages_sent":10000,"messages_received":10000,"connection_success":true,"total_latency_ms":15696.401604999906,"errors":[],"average_latency_ms":1.5696401604999906}
{"client_full_id":"client-job-go-8s-100c-10000m-5-xx65c-68","server_ip":"server-service","server_port":8080,"messages_sent":10000,"messages_received":10000,"connection_success":true,"total_latency_ms":15625.861047999977,"errors":[],"average_latency_ms":1.5625861047999976}
{"client_full_id":"client-job-go-8s-100c-10000m-5-xx65c-43","server_ip":"server-service","server_port":8080,"messages_sent":10000,"messages_received":10000,"connection_success":true,"total_latency_ms":15673.271984000006,"errors":[],"average_latency_ms":1.5673271984000006}
{"client_full_id":"client-job-go-8s-100c-10000m-5-xx65c-35","server_ip":"server-service","server_port":8080,"messages_sent":10000,"messages_received":10000,"connection_success":true,"total_latency_ms":15643.844636999986,"errors":[],"average_latency_ms":1.5643844636999986}
{"client_full_id":"client-job-go-8s-100c-10000m-5-xx65c-0","server_ip":"server-service","server_port":8080,"messages_sent":10000,"messages_received":10000,"connection_success":true,"total_latency_ms":15711.755663999977,"errors":[],"average_latency_ms":1.5711755663999976}
{"client_full_id":"client-job-go-8s-100c-10000m-5-xx65c-59","server_ip":"server-service","server_port":8080,"messages_sent":10000,"messages_received":10000,"connection_success":true,"total_latency_ms":15697.406561999973,"errors":[],"average_latency_ms":1.5697406561999974}
{"client_full_id":"client-job-go-8s-100c-10000m-5-xx65c-49","server_ip":"server-service","server_port":8080,"messages_sent":10000,"messages_received":10000,"connection_success":true,"total_latency_ms":15599.880229000071,"errors":[],"average_latency_ms":1.5599880229000072}
