{"client_full_id":"client-job-go-4s-50c-1m-8-6qqdr-46","server_ip":"server-service","server_port":8080,"messages_sent":1,"messages_received":1,"connection_success":true,"total_latency_ms":0.360185,"errors":[],"average_latency_ms":0.360185}
{"client_full_id":"client-job-go-4s-50c-1m-8-6qqdr-42","server_ip":"server-service","server_port":8080,"messages_sent":1,"messages_received":1,"connection_success":true,"total_latency_ms":0.942898,"errors":[],"average_latency_ms":0.942898}
{"client_full_id":"client-job-go-4s-50c-1m-8-6qqdr-14","server_ip":"server-service","server_port":8080,"messages_sent":1,"messages_received":1,"connection_success":true,"total_latency_ms":0.178872,"errors":[],"average_latency_ms":0.178872}
{"client_full_id":"client-job-go-4s-50c-1m-8-6qqdr-48","server_ip":"server-service","server_port":8080,"messages_sent":1,"messages_received":1,"connection_success":true,"total_latency_ms":0.360561,"errors":[],"average_latency_ms":0.360561}
{"client_full_id":"client-job-go-4s-50c-1m-8-6qqdr-33","server_ip":"server-service","server_port":8080,"messages_sent":1,"messages_received":1,"connection_success":true,"total_latency_ms":0.43951,"errors":[],"average_latency_ms":0.43951}
{"client_full_id":"client-job-go-4s-50c-1m-8-6qqdr-5","server_ip":"server-service","server_port":8080,"messages_sent":1,"messages_received":1,"connection_success":true,"total_latency_ms":0.511749,"errors":[],"average_latency_ms":0.511749}
{"client_full_id":"client-job-go-4s-50c-1m-8-6qqdr-41","server_ip":"server-service","server_port":8080,"messages_sent":1,"messages_received":1,"connection_success":true,"total_latency_ms":0.132838,"errors":[],"average_latency_ms":0.132838}
{"client_full_id":"client-job-go-4s-50c-1m-8-6qqdr-32","server_ip":"server-service","server_port":8080,"messages_sent":1,"messages_received":1,"connection_success":true,"total_latency_ms":0.291583,"errors":[],"average_latency_ms":0.291583}
{"client_full_id":"client-job-go-4s-50c-1m-8-6qqdr-40","server_ip":"server-service","server_port":8080,"messages_sent":1,"messages_received":1,"connection_success":true,"total_latency_ms":1.544008,"errors":[],"average_latency_ms":1.544008}
{"client_full_id":"client-job-go-4s-50c-1m-8-6qqdr-18","server_ip":"server-service","server_port":8080,"messages_sent":1,"messages_received":1,"connection_success":true,"total_latency_ms":0.170375,"errors":[],"average_latency_ms":0.170375}
{"client_full_id":"client-job-go-4s-50c-1m-8-6qqdr-45","server_ip":"server-service","server_port":8080,"messages_sent":1,"messages_received":1,"connection_success":true,"total_latency_ms":0.553405,"errors":[],"average_latency_ms":0.553405}
{"client_full_id":"client-job-go-4s-50c-1m-8-6qqdr-10","server_ip":"server-service","server_port":8080,"messages_sent":1,"messages_received":1,"connection_success":true,"total_latency_ms":0.240451,"errors":[],"average_latency_ms":0.240451}
{"client_full_id":"client-job-go-4s-50c-1m-8-6qqdr-38","server_ip":"server-service","server_port":8080,"messages_sent":1,"messages_received":1,"connection_success":true,"total_latency_ms":0.482783,"errors":[],"average_latency_ms":0.482783}
{"client_full_id":"client-job-go-4s-50c-1m-8-6qqdr-49","server_ip":"server-service","server_port":8080,"messages_sent":1,"messages_received":1,"connection_success":true,"total_latency_ms":1.926708,"errors":[],"average_latency_ms":1.926708}
{"client_full_id":"client-job-go-4s-50c-1m-8-6qqdr-16","server_ip":"server-service","server_port":8080,"messages_sent":1,"messages_received":1,"connection_success":true,"total_latency_ms":1.069922,"errors":[],"average_latency_ms":1.069922}
{"client_full_id":"client-job-go-4s-50c-1m-8-6qqdr-25","server_ip":"server-service","server_port":8080,"messages_sent":1,"messages_received":1,"connection_success":true,"total_latency_ms":0.71128,"errors":[],"average_latency_ms":0.71128}
{"client_full_id":"client-job-go-4s-50c-1m-8-6qqdr-39","server_ip":"server-service","server_port":8080,"messages_sent":1,"messages_received":1,"connection_success":true,"total_latency_ms":0.913024,"errors":[],"average_latency_ms":0.913024}
{"client_full_id":"client-job-go-4s-50c-1m-8-6qqdr-1","server_ip":"server-service","server_port":8080,"messages_sent":1,"messages_received":1,"connection_success":true,"total_latency_ms":0.347251,"errors":[],"average_latency_ms":0.347251}
{"client_full_id":"client-job-go-4s-50c-1m-8-6qqdr-37","server_ip":"server-service","server_port":8080,"messages_sent":1,"messages_received":1,"connection_success":true,"total_latency_ms":1.454841,"errors":[],"average_latency_ms":1.454841}
{"client_full_id":"client-job-go-4s-50c-1m-8-6qqdr-0","server_ip":"server-service","server_port":8080,"messages_sent":1,"messages_received":1,"connection_success":true,"total_latency_ms":0.187353,"errors":[],"average_latency_ms":0.187353}
{"client_full_id":"client-job-go-4s-50c-1m-8-6qqdr-44","server_ip":"server-service","server_port":8080,"messages_sent":1,"messages_received":1,"connection_success":true,"total_latency_ms":1.455632,"errors":[],"average_latency_ms":1.455632}
{"client_full_id":"client-job-go-4s-50c-1m-8-6qqdr-2","server_ip":"server-service","server_port":8080,"messages_sent":1,"messages_received":1,"connection_success":true,"total_latency_ms":1.260462,"errors":[],"average_latency_ms":1.260462}
{"client_full_id":"client-job-go-4s-50c-1m-8-6qqdr-11","server_ip":"server-service","server_port":8080,"messages_sent":1,"messages_received":1,"connection_success":true,"total_latency_ms":1.400302,"errors":[],"average_latency_ms":1.400302}
{"client_full_id":"client-job-go-4s-50c-1m-8-6qqdr-9","server_ip":"server-service","server_port":8080,"messages_sent":1,"messages_received":1,"connection_success":true,"total_latency_ms":0.545572,"errors":[],"average_latency_ms":0.545572}
{"client_full_id":"client-job-go-4s-50c-1m-8-6qqdr-24","server_ip":"server-service","server_port":8080,"messages_sent":1,"messages_received":1,"connection_success":true,"total_latency_ms":0.520207,"errors":[],"average_latency_ms":0.520207}
{"client_full_id":"client-job-go-4s-50c-1m-8-6qqdr-19","server_ip":"server-service","server_port":8080,"messages_sent":1,"messages_received":1,"connection_success":true,"total_latency_ms":0.696727,"errors":[],"average_latency_ms":0.696727}
{"client_full_id":"client-job-go-4s-50c-1m-8-6qqdr-21","server_ip":"server-service","server_port":8080,"messages_sent":1,"messages_received":1,"connection_success":true,"total_latency_ms":1.315512,"errors":[],"average_latency_ms":1.315512}
{"client_full_id":"client-job-go-4s-50c-1m-8-6qqdr-17","server_ip":"server-service","server_port":8080,"messages_sent":1,"messages_received":1,"connection_success":true,"total_latency_ms":2.087812,"errors":[],"average_latency_ms":2.087812}
{"client_full_id":"client-job-go-4s-50c-1m-8-6qqdr-27","server_ip":"server-service","server_port":8080,"messages_sent":1,"messages_received":1,"connection_success":true,"total_latency_ms":1.147282,"errors":[],"average_latency_ms":1.147282}
{"client_full_id":"client-job-go-4s-50c-1m-8-6qqdr-43","server_ip":"server-service","server_port":8080,"messages_sent":1,"messages_received":1,"connection_success":true,"total_latency_ms":1.997943,"errors":[],"average_latency_ms":1.997943}
{"client_full_id":"client-job-go-4s-50c-1m-8-6qqdr-4","server_ip":"server-service","server_port":8080,"messages_sent":1,"messages_received":1,"connection_success":true,"total_latency_ms":2.035141,"errors":[],"average_latency_ms":2.035141}
{"client_full_id":"client-job-go-4s-50c-1m-8-6qqdr-47","server_ip":"server-service","server_port":8080,"messages_sent":1,"messages_received":1,"connection_success":true,"total_latency_ms":1.808573,"errors":[],"average_latency_ms":1.808573}
{"client_full_id":"client-job-go-4s-50c-1m-8-6qqdr-8","server_ip":"server-service","server_port":8080,"messages_sent":1,"messages_received":1,"connection_success":true,"total_latency_ms":1.556072,"errors":[],"average_latency_ms":1.556072}
{"client_full_id":"client-job-go-4s-50c-1m-8-6qqdr-34","server_ip":"server-service","server_port":8080,"messages_sent":1,"messages_received":1,"connection_success":true,"total_latency_ms":1.478206,"errors":[],"average_latency_ms":1.478206}
{"client_full_id":"client-job-go-4s-50c-1m-8-6qqdr-6","server_ip":"server-service","server_port":8080,"messages_sent":1,"messages_received":1,"connection_success":true,"total_latency_ms":1.585518,"errors":[],"average_latency_ms":1.585518}
{"client_full_id":"client-job-go-4s-50c-1m-8-6qqdr-28","server_ip":"server-service","server_port":8080,"messages_sent":1,"messages_received":1,"connection_success":true,"total_latency_ms":1.808285,"errors":[],"average_latency_ms":1.808285}
{"client_full_id":"client-job-go-4s-50c-1m-8-6qqdr-23","server_ip":"server-service","server_port":8080,"messages_sent":1,"messages_received":1,"connection_success":true,"total_latency_ms":2.157317,"errors":[],"average_latency_ms":2.157317}
{"client_full_id":"client-job-go-4s-50c-1m-8-6qqdr-26","server_ip":"server-service","server_port":8080,"messages_sent":1,"messages_received":1,"connection_success":true,"total_latency_ms":2.435181,"errors":[],"average_latency_ms":2.435181}
{"client_full_id":"client-job-go-4s-50c-1m-8-6qqdr-3","server_ip":"server-service","server_port":8080,"messages_sent":1,"messages_received":1,"connection_success":true,"total_latency_ms":0.576035,"errors":[],"average_latency_ms":0.576035}
{"client_full_id":"client-job-go-4s-50c-1m-8-6qqdr-20","server_ip":"server-service","server_port":8080,"messages_sent":1,"messages_received":1,"connection_success":true,"total_latency_ms":0.392817,"errors":[],"average_latency_ms":0.392817}
{"client_full_id":"client-job-go-4s-50c-1m-8-6qqdr-12","server_ip":"server-service","server_port":8080,"messages_sent":1,"messages_received":1,"connection_success":true,"total_latency_ms":2.559356,"errors":[],"average_latency_ms":2.559356}
{"client_full_id":"client-job-go-4s-50c-1m-8-6qqdr-13","server_ip":"server-service","server_port":8080,"messages_sent":1,"messages_received":1,"connection_success":true,"total_latency_ms":2.499844,"errors":[],"average_latency_ms":2.499844}
{"client_full_id":"client-job-go-4s-50c-1m-8-6qqdr-35","server_ip":"server-service","server_port":8080,"messages_sent":1,"messages_received":1,"connection_success":true,"total_latency_ms":2.040695,"errors":[],"average_latency_ms":2.040695}
{"client_full_id":"client-job-go-4s-50c-1m-8-6qqdr-22","server_ip":"server-service","server_port":8080,"messages_sent":1,"messages_received":1,"connection_success":true,"total_latency_ms":0.117554,"errors":[],"average_latency_ms":0.117554}
{"client_full_id":"client-job-go-4s-50c-1m-8-6qqdr-15","server_ip":"server-service","server_port":8080,"messages_sent":1,"messages_received":1,"connection_success":true,"total_latency_ms":2.667385,"errors":[],"average_latency_ms":2.667385}
{"client_full_id":"client-job-go-4s-50c-1m-8-6qqdr-36","server_ip":"server-service","server_port":8080,"messages_sent":1,"messages_received":1,"connection_success":true,"total_latency_ms":2.569997,"errors":[],"average_latency_ms":2.569997}
{"client_full_id":"client-job-go-4s-50c-1m-8-6qqdr-7","server_ip":"server-service","server_port":8080,"messages_sent":1,"messages_received":1,"connection_success":true,"total_latency_ms":1.838258,"errors":[],"average_latency_ms":1.838258}
{"client_full_id":"client-job-go-4s-50c-1m-8-6qqdr-30","server_ip":"server-service","server_port":8080,"messages_sent":1,"messages_received":1,"connection_success":true,"total_latency_ms":1.988443,"errors":[],"average_latency_ms":1.988443}
{"client_full_id":"client-job-go-4s-50c-1m-8-6qqdr-31","server_ip":"server-service","server_port":8080,"messages_sent":1,"messages_received":1,"connection_success":true,"total_latency_ms":2.094965,"errors":[],"average_latency_ms":2.094965}
{"client_full_id":"client-job-go-4s-50c-1m-8-6qqdr-29","server_ip":"server-service","server_port":8080,"messages_sent":1,"messages_received":1,"connection_success":true,"total_latency_ms":2.518455,"errors":[],"average_latency_ms":2.518455}
