{"client_full_id":"client-job-go-10s-20c-10m-1-6xcrh-12","server_ip":"server-service","server_port":8080,"messages_sent":10,"messages_received":10,"connection_success":true,"total_latency_ms":3.401388,"errors":[],"average_latency_ms":0.34013879999999996}
{"client_full_id":"client-job-go-10s-20c-10m-1-6xcrh-16","server_ip":"server-service","server_port":8080,"messages_sent":10,"messages_received":10,"connection_success":true,"total_latency_ms":2.512491,"errors":[],"average_latency_ms":0.2512491}
{"client_full_id":"client-job-go-10s-20c-10m-1-6xcrh-7","server_ip":"server-service","server_port":8080,"messages_sent":10,"messages_received":10,"connection_success":true,"total_latency_ms":3.362648,"errors":[],"average_latency_ms":0.33626480000000003}
{"client_full_id":"client-job-go-10s-20c-10m-1-6xcrh-6","server_ip":"server-service","server_port":8080,"messages_sent":10,"messages_received":10,"connection_success":true,"total_latency_ms":3.821835,"errors":[],"average_latency_ms":0.3821835}
{"client_full_id":"client-job-go-10s-20c-10m-1-6xcrh-1","server_ip":"server-service","server_port":8080,"messages_sent":10,"messages_received":10,"connection_success":true,"total_latency_ms":4.144571999999999,"errors":[],"average_latency_ms":0.4144571999999999}
{"client_full_id":"client-job-go-10s-20c-10m-1-6xcrh-19","server_ip":"server-service","server_port":8080,"messages_sent":10,"messages_received":10,"connection_success":true,"total_latency_ms":5.243939,"errors":[],"average_latency_ms":0.5243939}
{"client_full_id":"client-job-go-10s-20c-10m-1-6xcrh-5","server_ip":"server-service","server_port":8080,"messages_sent":10,"messages_received":10,"connection_success":true,"total_latency_ms":4.867633,"errors":[],"average_latency_ms":0.48676329999999995}
{"client_full_id":"client-job-go-10s-20c-10m-1-6xcrh-18","server_ip":"server-service","server_port":8080,"messages_sent":10,"messages_received":10,"connection_success":true,"total_latency_ms":5.402173999999999,"errors":[],"average_latency_ms":0.5402173999999998}
{"client_full_id":"client-job-go-10s-20c-10m-1-6xcrh-15","server_ip":"server-service","server_port":8080,"messages_sent":10,"messages_received":10,"connection_success":true,"total_latency_ms":3.629297,"errors":[],"average_latency_ms":0.3629297}
{"client_full_id":"client-job-go-10s-20c-10m-1-6xcrh-17","server_ip":"server-service","server_port":8080,"messages_sent":10,"messages_received":10,"connection_success":true,"total_latency_ms":4.850514,"errors":[],"average_latency_ms":0.4850514}
{"client_full_id":"client-job-go-10s-20c-10m-1-6xcrh-13","server_ip":"server-service","server_port":8080,"messages_sent":10,"messages_received":10,"connection_success":true,"total_latency_ms":3.880842999999999,"errors":[],"average_latency_ms":0.38808429999999994}
{"client_full_id":"client-job-go-10s-20c-10m-1-6xcrh-14","server_ip":"server-service","server_port":8080,"messages_sent":10,"messages_received":10,"connection_success":true,"total_latency_ms":5.304250000000001,"errors":[],"average_latency_ms":0.530425}
{"client_full_id":"client-job-go-10s-20c-10m-1-6xcrh-8","server_ip":"server-service","server_port":8080,"messages_sent":10,"messages_received":10,"connection_success":true,"total_latency_ms":6.158724000000001,"errors":[],"average_latency_ms":0.6158724000000001}
{"client_full_id":"client-job-go-10s-20c-10m-1-6xcrh-9","server_ip":"server-service","server_port":8080,"messages_sent":10,"messages_received":10,"connection_success":true,"total_latency_ms":4.666508,"errors":[],"average_latency_ms":0.46665080000000003}
{"client_full_id":"client-job-go-10s-20c-10m-1-6xcrh-2","server_ip":"server-service","server_port":8080,"messages_sent":10,"messages_received":10,"connection_success":true,"total_latency_ms":6.967005000000001,"errors":[],"average_latency_ms":0.6967005000000002}
{"client_full_id":"client-job-go-10s-20c-10m-1-6xcrh-0","server_ip":"server-service","server_port":8080,"messages_sent":10,"messages_received":10,"connection_success":true,"total_latency_ms":6.730060000000001,"errors":[],"average_latency_ms":0.6730060000000001}
{"client_full_id":"client-job-go-10s-20c-10m-1-6xcrh-10","server_ip":"server-service","server_port":8080,"messages_sent":10,"messages_received":10,"connection_success":true,"total_latency_ms":6.209419,"errors":[],"average_latency_ms":0.6209418999999999}
{"client_full_id":"client-job-go-10s-20c-10m-1-6xcrh-11","server_ip":"server-service","server_port":8080,"messages_sent":10,"messages_received":10,"connection_success":true,"total_latency_ms":6.841156,"errors":[],"average_latency_ms":0.6841155999999999}
{"client_full_id":"client-job-go-10s-20c-10m-1-6xcrh-4","server_ip":"server-service","server_port":8080,"messages_sent":10,"messages_received":10,"connection_success":true,"total_latency_ms":5.3863080000000005,"errors":[],"average_latency_ms":0.5386308000000001}
{"client_full_id":"client-job-go-10s-20c-10m-1-6xcrh-3","server_ip":"server-service","server_port":8080,"messages_sent":10,"messages_received":10,"connection_success":true,"total_latency_ms":6.653834000000001,"errors":[],"average_latency_ms":0.6653834000000001}
